unit_test/__init__.py
unittest3-0.0.0a0.dist-info/licenses/LICENSE.txt
unittest3-0.0.0a0.dist-info/WHEEL
unittest3-0.0.0a0.dist-info/METADATA
unittest3-0.0.0a0.dist-info/RECORD
